marketminer/__init__.py
marketminer/fundamentals_scraper.py
marketminer/news_scraper.py
marketminer/utils.py
marketminer-0.4.0.dist-info/METADATA
marketminer-0.4.0.dist-info/WHEEL
marketminer-0.4.0.dist-info/top_level.txt
marketminer-0.4.0.dist-info/RECORD
