Metadata-Version: 2.4
Name: marketminer
Version: 0.4.0
Summary: A Python library for scraping financial data from various sources.
Home-page: https://github.com/vaibhavjha100/marketminer
Author: Vaibhav Jha
Author-email: vaibhavjha100@gmail.com
License: MIT
Classifier: Programming Language :: Python :: 3
Classifier: License :: OSI Approved :: MIT License
Classifier: Operating System :: OS Independent
Classifier: Topic :: Software Development :: Libraries
Classifier: Intended Audience :: Financial and Insurance Industry
Requires-Python: >=3.7
Requires-Dist: requests
Requires-Dist: beautifulsoup4
Requires-Dist: pandas
Requires-Dist: aiohttp
Requires-Dist: nest_asyncio
Requires-Dist: selenium
Dynamic: author
Dynamic: author-email
Dynamic: classifier
Dynamic: description
Dynamic: description-content-type
Dynamic: home-page
Dynamic: license
Dynamic: requires-dist
Dynamic: requires-python
Dynamic: summary
